{
  "name": "Squad",
  "price": "R$ 200,00",
  "description": "Quatro ingressos para ir com seu time",
  "icon": "Rocket",
  "featured": false,
  "badge": "",
  "ctaLabel": "Comprar Squad",
  "ctaUrl": "https://sympla.com.br/evento/aws-community-day-norte-2026",
  "note": "",
  "benefits": [
    { "item": "4 ingressos individuais" },
    { "item": "Economia de R$ 40,00" },
    { "item": "Acesso completo ao evento" },
    { "item": "Kit do participante para cada" },
    { "item": "Certificado digital para cada" },
    { "item": "Lugar reservado na frente" }
  ],
  "order": 4
}
